{
  "project_info": {
    "project_number": "860632101251",
    "project_id": "quanlyphongtro-c49f5",
    "storage_bucket": "quanlyphongtro-c49f5.appspot.com"
  },
  "client": [
    {
      "client_info": {
        "mobilesdk_app_id": "1:860632101251:android:edf4e78390c5390c1f86b6",
        "android_client_info": {
          "package_name": "QLPhongTro.com"
        }
      },
      "oauth_client": [],
      "api_key": [
        {
          "current_key": "AIzaSyD97QPh7JdxhIQXZ74q8mxp2BBAVgyzWFY"
        }
      ],
      "services": {
        "appinvite_service": {
          "other_platform_oauth_client": []
        }
      }
    }
  ],
  "configuration_version": "1"
}